flash_pop/__init__.py
flash_pop/diffusion_retnet.py
flash_pop/pop_retnet.py
flash_pop/recurrent_state.py
flash_pop/retnet.py
flash_pop/utils.py
flash_pop/xpos_emb.py
flash_pop/fused_retention/__init__.py
flash_pop/fused_retention/fused_chunk_bwd.py
flash_pop/fused_retention/fused_chunk_fwd.py
flash_pop/fused_retention/reference.py
flash_pop/modules/__init__.py
flash_pop/modules/adaln.py
flash_pop/modules/timestep.py
flash_pop/pop_retention/__init__.py
flash_pop/pop_retention/pop_bwd.py
flash_pop/pop_retention/pop_fwd.py
flash_pop/pop_retention/reference.py
flash_pop-0.3.0.dist-info/METADATA
flash_pop-0.3.0.dist-info/WHEEL
flash_pop-0.3.0.dist-info/licenses/LICENSE
flash_pop-0.3.0.dist-info/RECORD
