Metadata-Version: 2.4
Name: flash-pop
Version: 0.3.0
Summary: A hardware-aware efficient implementation of RetNet and POP.
Author-email: Lior Cohen <liorcohen5@campus.technion.ac.il>
License: GPL-3.0-or-later
License-File: LICENSE
Requires-Python: >=3.10
Requires-Dist: einops
Requires-Dist: loguru
Requires-Dist: tilelang>=0.1.3
Requires-Dist: torch>=2.1.0
